flask_triangle/__init__.py
flask_triangle/form.py
flask_triangle/jinja.py
flask_triangle/modifier.py
flask_triangle/schema.py
flask_triangle/triangle.py
flask_triangle/widget.py
flask_triangle/helpers/__init__.py
flask_triangle/helpers/html.py
flask_triangle/helpers/python3.py
flask_triangle/modifiers/__init__.py
flask_triangle/modifiers/limits.py
flask_triangle/modifiers/multiple.py
flask_triangle/modifiers/noschema.py
flask_triangle/modifiers/patterns.py
flask_triangle/modifiers/required.py
flask_triangle/modifiers/types.py
flask_triangle/widgets/__init__.py
flask_triangle/widgets/special/__init__.py
flask_triangle/widgets/special/label.py
flask_triangle/widgets/special/nowidget.py
flask_triangle/widgets/standard/__init__.py
flask_triangle/widgets/standard/select.py
flask_triangle/widgets/standard/text.py
flask_triangle/widgets/uibootstrap/__init__.py
flask_triangle/widgets/uibootstrap/datepicker.py
flask_triangle/widgets/uibootstrap/typeahead.py
tests/__init__.py
tests/test_helpers/__init__.py
tests/test_helpers/html.py
tests/test_jinja/__init__.py
tests/test_jinja/cond.py
tests/test_jinja/filter.py
Flask_Triangle_OctoKrishna-0.5.5.dist-info/AUTHORS
Flask_Triangle_OctoKrishna-0.5.5.dist-info/METADATA
Flask_Triangle_OctoKrishna-0.5.5.dist-info/WHEEL
Flask_Triangle_OctoKrishna-0.5.5.dist-info/top_level.txt
Flask_Triangle_OctoKrishna-0.5.5.dist-info/RECORD
