Metadata-Version: 2.1
Name: Flask-Triangle-OctoKrishna
Version: 0.5.5
Summary: Integration of AngularJS and Flask, originally created by Morgan Delahaye-Prat (mdp@m-del.fr).
Home-page: https://github.com/robinschoss/flask-triangle
Author: Krishna Y
Author-email: webkrishna@outlook.com
License: BSD
Platform: any
Classifier: Development Status :: 4 - Beta
Classifier: Environment :: Web Environment
Classifier: Intended Audience :: Developers
Classifier: License :: OSI Approved :: BSD License
Classifier: Operating System :: OS Independent
Classifier: Programming Language :: Python
Classifier: Topic :: Internet :: WWW/HTTP :: Dynamic Content
Classifier: Topic :: Software Development :: Libraries :: Python Modules
Requires-Dist: flask
Requires-Dist: jsonschema
